ciborg/__init__.py
ciborg/__main__.py
ciborg/_version.py
ciborg/azure.py
ciborg/cli.py
ciborg/configuration.py
ciborg/py.typed
ciborg/data/__init__.py
ciborg/data/azure-pipelines.yml
ciborg/data/azure.yml
ciborg/data/ciborg.json
ciborg/tests/__init__.py
ciborg/tests/test_azure.py
ciborg-0.1.dist-info/LICENSE
ciborg-0.1.dist-info/METADATA
ciborg-0.1.dist-info/WHEEL
ciborg-0.1.dist-info/entry_points.txt
ciborg-0.1.dist-info/top_level.txt
ciborg-0.1.dist-info/RECORD
