Metadata-Version: 2.1
Name: ciborg
Version: 0.1
Summary: Generate CI configuration for various services
Home-page: https://github.com/altendky/ciborg
Author: Kyle Altendorf
Author-email: sda@fstab.net
License: MIT
Platform: UNKNOWN
Classifier: Development Status :: 3 - Alpha
Classifier: Intended Audience :: Developers
Classifier: License :: OSI Approved :: MIT License
Classifier: Programming Language :: Python :: 3
Classifier: Programming Language :: Python :: 3.5
Classifier: Programming Language :: Python :: 3.6
Classifier: Programming Language :: Python :: 3.7
Classifier: Operating System :: POSIX :: Linux
Classifier: Operating System :: MacOS
Classifier: Operating System :: Microsoft :: Windows
Requires-Python: >=3.5
Requires-Dist: attrs
Requires-Dist: click
Requires-Dist: importlib-resources
Requires-Dist: marshmallow
Requires-Dist: marshmallow-polyfield
Requires-Dist: pyrsistent
Requires-Dist: pyyaml
Provides-Extra: dev
Requires-Dist: gitignoreio ; extra == 'dev'
Requires-Dist: coverage ; extra == 'dev'
Requires-Dist: mypy ; extra == 'dev'
Requires-Dist: pytest ; extra == 'dev'
Requires-Dist: pytest-cov ; extra == 'dev'
Requires-Dist: tox ; extra == 'dev'
Provides-Extra: test
Requires-Dist: coverage ; extra == 'test'
Requires-Dist: mypy ; extra == 'test'
Requires-Dist: pytest ; extra == 'test'
Requires-Dist: pytest-cov ; extra == 'test'
Requires-Dist: tox ; extra == 'test'
